primescython/__init__.py
primescython/primes.pyx
primescython/setup.py
primescython-0.0.5.dist-info/LICENSE
primescython-0.0.5.dist-info/METADATA
primescython-0.0.5.dist-info/WHEEL
primescython-0.0.5.dist-info/top_level.txt
primescython-0.0.5.dist-info/RECORD
