Metadata-Version: 2.1
Name: primescython
Version: 0.0.5
Summary: A cython test
Author-email: Marco Salvalaggio <marco.salvalaggio@bip-group.com>
Project-URL: Homepage, https://github.com/marcosalvalaggio-bip/test-cython-prines
Project-URL: Bug Tracker, https://github.com/marcosalvalaggio-bip/test-cython-prines/issues
Classifier: Programming Language :: Python :: 3
Classifier: License :: OSI Approved :: MIT License
Classifier: Operating System :: OS Independent
Requires-Python: >=3.7
License-File: LICENSE
